{
  "name": "IdCardManagement",
  "fields": [
    {
      "fieldName": "cardNo",
      "fieldType": "String"
    },
    {
      "fieldName": "issueDate",
      "fieldType": "LocalDate"
    },
    {
      "fieldName": "ticketNo",
      "fieldType": "String"
    },
    {
      "fieldName": "validTill",
      "fieldType": "LocalDate"
    }
  ],
  "relationships": [
    {
      "relationshipType": "many-to-one",
      "otherEntityName": "employee",
      "otherEntityRelationshipName": "idCardManagement",
      "relationshipName": "employee",
      "otherEntityField": "name"
    }
  ],
  "changelogDate": "20210327193102",
  "entityTableName": "id_card_management",
  "dto": "no",
  "pagination": "pagination",
  "service": "serviceClass",
  "jpaMetamodelFiltering": true,
  "fluentMethods": true,
  "readOnly": false,
  "embedded": false,
  "clientRootFolder": "",
  "applications": "*"
}
